README.rst
setup.py
bosta/__init__.py
bosta/base.py
bosta/client.py
bosta/deliveries.py
bosta/stone_base.py
bosta/stone_serializers.py
bosta/stone_validators.py
bosta.egg-info/PKG-INFO
bosta.egg-info/SOURCES.txt
bosta.egg-info/dependency_links.txt
bosta.egg-info/requires.txt
bosta.egg-info/top_level.txt