Metadata-Version: 1.2
Name: bosta
Version: 0.1.0
Summary: Bosta Python SDK
Home-page: https://github.com/Zbooni/bosta-sdk-python
Author: Zbooni
Author-email: tech@zbooni.com
License: BSD
Platform: UNKNOWN
Classifier: Development Status :: 4 - Beta
Classifier: Intended Audience :: Developers
Classifier: License :: OSI Approved :: BSD License
Classifier: Operating System :: OS Independent
Classifier: Programming Language :: Python :: 2.7
Classifier: Programming Language :: Python :: 3
Classifier: Programming Language :: Python :: Implementation :: CPython
Classifier: Topic :: Office/Business
Classifier: Topic :: Software Development :: Libraries :: Python Modules
Requires-Python: >=2.7
